testtestasdf/__init__.py
testtestasdf-0.0.3.dist-info/DESCRIPTION.rst
testtestasdf-0.0.3.dist-info/METADATA
testtestasdf-0.0.3.dist-info/RECORD
testtestasdf-0.0.3.dist-info/WHEEL
testtestasdf-0.0.3.dist-info/entry_points.txt
testtestasdf-0.0.3.dist-info/metadata.json
testtestasdf-0.0.3.dist-info/top_level.txt
