Metadata-Version: 2.0
Name: testtestasdf
Version: 0.0.3
Summary: testtestasdf
Home-page: UNKNOWN
Author: testtestasdf
Author-email: testtestasdf@gmail.com
License: UNKNOWN
Download-URL: https://github.com/testtestasdf/testtestasdf
Platform: UNKNOWN
Requires-Dist: requests
